{"index":{"0":0,"1":1,"2":2,"3":3,"4":4,"5":5,"6":6,"7":7,"8":8,"9":9,"10":10,"11":11,"12":12,"13":13,"14":14,"15":15,"16":16,"17":17,"18":18,"19":19,"20":20,"21":21,"22":22,"23":23,"24":24,"25":0,"26":0,"27":0,"28":0,"29":0,"30":0},"Product":{"0":"attack_potion(3)","1":"antipoison(3)","2":"strength_potion(3)","3":"compost_potion(3)","4":"restore_potion(3)","5":"energy_potion(3)","6":"agility_potion(3)","7":"combat_potion(3)","8":"prayer_potion(3)","9":"super_attack(3)","10":"superantipoison(3)","11":"fishing_potion(3)","12":"super_energy(3)","13":"hunter_potion(3)","14":"super_strength(3)","15":"super_restore(3)","16":"super_defence(3)","17":"antifire_potion(3)","18":"ranging_potion(3)","19":"magic_potion(3)","20":"bastion_potion(3)","21":"battlemage_potion(3)","22":"saradomin_brew(3)","23":"super_antifire_potion(4)","24":"anti-venom+(4)","25":"stamina_potion(4)","26":"extended_antifire(4)","27":"anti-venom(4)","28":"super_combat_potion(4)","29":"extended_super_antifire(4)","30":"serum_207"},"XP\/HR":{"0":62500.0,"1":93750.0,"2":125000.0,"3":150000.0,"4":156250.0,"5":168750.0,"6":200000.0,"7":210000.0,"8":218750.0,"9":250000.0,"10":265750.0,"11":281250.0,"12":293750.0,"13":300000.0,"14":312500.0,"15":356250.0,"16":375000.0,"17":393750.0,"18":406250.0,"19":431250.0,"20":387500.0,"21":387500.0,"22":450000.0,"23":325000.0,"24":312500.0,"25":255000.0,"26":275000.0,"27":300000.0,"28":324900.0,"29":400000.0,"30":125000.0},"GP\/HR":{"0":-277500,"1":-300000,"2":-792500,"3":-1335000,"4":-2527500,"5":-775000,"6":-7952500,"7":-995000,"8":-1007500,"9":-1202500,"10":-2407500,"11":-8845000,"12":-1395000,"13":-3122500,"14":-1870000,"15":-2512500,"16":-2412500,"17":-3135000,"18":-3410000,"19":-4372500,"20":-6510000,"21":-22110000,"22":-5012500,"23":-2740000,"24":-1312500,"25":-1960000,"26":-2415000,"27":-5135000,"28":-1481544,"29":-2735000,"30":-787500},"Cost":{"0":-111,"1":-120,"2":-317,"3":-534,"4":-1011,"5":-310,"6":-3181,"7":-398,"8":-403,"9":-481,"10":-963,"11":-3538,"12":-558,"13":-1249,"14":-748,"15":-1005,"16":-965,"17":-1254,"18":-1364,"19":-1749,"20":-2604,"21":-8844,"22":-2005,"23":-1096,"24":-525,"25":-784,"26":-966,"27":-2054,"28":-684,"29":-1094,"30":-315},"Base Ingredient":{"0":"guam_potion_(unf)","1":"marrentill_potion_(unf)","2":"tarromin_potion_(unf)","3":"harralander_potion_(unf)","4":"harralander_potion_(unf)","5":"harralander_potion_(unf)","6":"toadflax_potion_(unf)","7":"harralander_potion_(unf)","8":"ranarr_potion_(unf)","9":"irit_potion_(unf)","10":"irit_potion_(unf)","11":"avantoe_potion_(unf)","12":"avantoe_potion_(unf)","13":"avantoe_potion_(unf)","14":"kwuarm_potion_(unf)","15":"snapdragon_potion_(unf)","16":"cadantine_potion_(unf)","17":"lantadyme_potion_(unf)","18":"dwarf_weed_potion_(unf)","19":"lantadyme_potion_(unf)","20":"cadantine_blood_potion_(unf)","21":"cadantine_blood_potion_(unf)","22":"toadflax_potion_(unf)","23":"antifire_potion(4)","24":"anti-venom(4)","25":"super_energy(4)","26":"antifire_potion(4)","27":"antidote++(4)","28":"super_attack(4)","29":"super_antifire_potion(4)","30":"tarromin_potion_(unf)"},"Base Ingredient Cost":{"0":111,"1":67,"2":188,"3":473,"4":473,"5":473,"6":2983,"7":473,"8":6001,"9":1037,"10":1037,"11":3126,"12":3126,"13":3126,"14":2745,"15":6935,"16":2797,"17":1773,"18":1415,"19":1773,"20":22393,"21":22393,"22":2983,"23":901,"24":7139,"25":3791,"26":901,"27":6293,"28":806,"29":11518,"30":188},"Secondary Ingredient":{"0":"eye_of_newt","1":"unicorn_horn_dust","2":"limpwurt_root","3":"volcanic_ash","4":"red_spiders'_eggs","5":"chocolate_dust","6":"toad's_legs","7":"goat_horn_dust","8":"snape_grass","9":"eye_of_newt","10":"unicorn_horn_dust","11":"snape_grass","12":"mort_myre_fungus","13":"kebbit_teeth_dust","14":"limpwurt_root","15":"red_spiders'_eggs","16":"white_berries","17":"dragon_scale_dust","18":"wine_of_zamorak","19":"potato_cactus","20":"wine_of_zamorak","21":"potato_cactus","22":"crushed_nest","23":"crushed_superior_dragon_bones","24":"torstol","25":"amylase_crystal","26":"lava_scale_shard","27":"zulrah's_scales","28":"super_strength(4)","29":"lava_scale_shard","30":"ashes"},"Secondary Ingredient Cost":{"0":4,"1":190,"2":236,"3":70,"4":588,"5":44,"6":418,"7":115,"8":508,"9":4,"10":190,"11":508,"12":231,"13":3268,"14":236,"15":588,"16":455,"17":129,"18":815,"19":41,"20":815,"21":41,"22":5489,"23":11713,"24":3232,"25":1067,"26":70,"27":145,"28":2971,"29":70,"30":128},"Level":{"0":3,"1":5,"2":12,"3":22,"4":22,"5":26,"6":34,"7":36,"8":38,"9":45,"10":48,"11":50,"12":52,"13":53,"14":55,"15":63,"16":66,"17":69,"18":72,"19":76,"20":80,"21":80,"22":81,"23":92,"24":94,"25":77,"26":84,"27":87,"28":90,"29":98,"30":15}}